source_amazon_ads/__init__.py
source_amazon_ads/manifest.yaml
source_amazon_ads/run.py
source_amazon_ads/schemas/attribution_report_performance_adgroup.json
source_amazon_ads/schemas/attribution_report_performance_campaign.json
source_amazon_ads/schemas/attribution_report_performance_creative.json
source_amazon_ads/schemas/attribution_report_products.json
source_amazon_ads/schemas/portfolios.json
source_amazon_ads/schemas/profiles.json
source_amazon_ads/schemas/sponsored_brands_ad_groups.json
source_amazon_ads/schemas/sponsored_brands_campaigns.json
source_amazon_ads/schemas/sponsored_brands_keywords.json
source_amazon_ads/schemas/sponsored_brands_v3_report_stream.json
source_amazon_ads/schemas/sponsored_brands_v3_report_stream_daily.json
source_amazon_ads/schemas/sponsored_display_ad_groups.json
source_amazon_ads/schemas/sponsored_display_adgroups_report_stream.json
source_amazon_ads/schemas/sponsored_display_adgroups_report_stream_daily.json
source_amazon_ads/schemas/sponsored_display_asins_report_stream.json
source_amazon_ads/schemas/sponsored_display_asins_report_stream_daily.json
source_amazon_ads/schemas/sponsored_display_budget_rules.json
source_amazon_ads/schemas/sponsored_display_campaigns.json
source_amazon_ads/schemas/sponsored_display_campaigns_report_stream.json
source_amazon_ads/schemas/sponsored_display_campaigns_report_stream_daily.json
source_amazon_ads/schemas/sponsored_display_creatives.json
source_amazon_ads/schemas/sponsored_display_product_ads.json
source_amazon_ads/schemas/sponsored_display_productads_report_stream.json
source_amazon_ads/schemas/sponsored_display_productads_report_stream_daily.json
source_amazon_ads/schemas/sponsored_display_targetings.json
source_amazon_ads/schemas/sponsored_display_targets_report_stream.json
source_amazon_ads/schemas/sponsored_display_targets_report_stream_daily.json
source_amazon_ads/schemas/sponsored_product_ad_group_bid_recommendations.json
airbyte_source_amazon_ads-7.2.3.dist-info/METADATA
airbyte_source_amazon_ads-7.2.3.dist-info/WHEEL
airbyte_source_amazon_ads-7.2.3.dist-info/entry_points.txt
airbyte_source_amazon_ads-7.2.3.dist-info/RECORD
