Metadata-Version: 2.3
Name: airbyte-source-amazon-ads
Version: 7.2.3
Summary: Source implementation for Amazon Ads.
License: MIT
Author: Airbyte
Author-email: contact@airbyte.io
Requires-Python: >=3.10,<3.12
Classifier: License :: OSI Approved :: MIT License
Classifier: Programming Language :: Python :: 3
Classifier: Programming Language :: Python :: 3.10
Classifier: Programming Language :: Python :: 3.11
Requires-Dist: airbyte-cdk (>=6.45.10,<7.0.0)
Project-URL: Documentation, https://docs.airbyte.com/integrations/sources/amazon-ads
Project-URL: Homepage, https://airbyte.com
Project-URL: Repository, https://github.com/airbytehq/airbyte
